platon_daytona/__init__.py
platon_daytona/_async/__init__.py
platon_daytona/_async/daytona.py
platon_daytona/_async/filesystem.py
platon_daytona/_async/git.py
platon_daytona/_async/lsp_server.py
platon_daytona/_async/object_storage.py
platon_daytona/_async/process.py
platon_daytona/_async/sandbox.py
platon_daytona/_async/snapshot.py
platon_daytona/_async/volume.py
platon_daytona/_sync/__init__.py
platon_daytona/_sync/daytona.py
platon_daytona/_sync/filesystem.py
platon_daytona/_sync/git.py
platon_daytona/_sync/lsp_server.py
platon_daytona/_sync/object_storage.py
platon_daytona/_sync/process.py
platon_daytona/_sync/sandbox.py
platon_daytona/_sync/snapshot.py
platon_daytona/_sync/volume.py
platon_daytona/_utils/__init__.py
platon_daytona/_utils/chart_data_extractor_wrapper.py
platon_daytona/_utils/deprecation.py
platon_daytona/_utils/docs_ignore.py
platon_daytona/_utils/enum.py
platon_daytona/_utils/errors.py
platon_daytona/_utils/path.py
platon_daytona/_utils/stream.py
platon_daytona/_utils/timeout.py
platon_daytona/code_toolbox/__init__.py
platon_daytona/code_toolbox/sandbox_python_code_toolbox.py
platon_daytona/code_toolbox/sandbox_ts_code_toolbox.py
platon_daytona/common/__init__.py
platon_daytona/common/charts.py
platon_daytona/common/daytona.py
platon_daytona/common/errors.py
platon_daytona/common/filesystem.py
platon_daytona/common/git.py
platon_daytona/common/image.py
platon_daytona/common/lsp_server.py
platon_daytona/common/process.py
platon_daytona/common/protocols.py
platon_daytona/common/sandbox.py
platon_daytona/common/snapshot.py
platon_daytona/common/volume.py
platon_daytona-0.1.5.dist-info/LICENSE
platon_daytona-0.1.5.dist-info/METADATA
platon_daytona-0.1.5.dist-info/WHEEL
platon_daytona-0.1.5.dist-info/RECORD
