Metadata-Version: 2.3
Name: platon-daytona
Version: 0.1.5
Summary: Python SDK for Daytona, forked by platon.ai with enhanced features
License: Apache-2.0
Keywords: daytona,sdk,platon,sandbox,development,ai
Author: Daytona Platforms Inc.
Author-email: support@daytona.io
Maintainer: Platon.AI
Maintainer-email: ivincent.zhang@gmail.com
Requires-Python: >=3.8,<4.0
Classifier: Development Status :: 4 - Beta
Classifier: Intended Audience :: Developers
Classifier: License :: OSI Approved :: Apache Software License
Classifier: Operating System :: OS Independent
Classifier: Programming Language :: Python
Classifier: Programming Language :: Python :: 3
Classifier: Programming Language :: Python :: 3.8
Classifier: Programming Language :: Python :: 3.9
Classifier: Programming Language :: Python :: 3.10
Classifier: Programming Language :: Python :: 3.11
Classifier: Programming Language :: Python :: 3.12
Classifier: Programming Language :: Python :: 3.13
Classifier: Topic :: Software Development :: Libraries :: Python Modules
Classifier: Topic :: System :: Distributed Computing
Requires-Dist: Deprecated (>=1.2.18,<2.0.0)
Requires-Dist: aioboto3 (>=13.0.0,<15.0.0)
Requires-Dist: aiofiles (>=24.1.0,<24.2.0)
Requires-Dist: boto3 (>=1.0.0,<2.0.0)
Requires-Dist: environs (>=10.0.0,<15.0.0)
Requires-Dist: httpx (>=0.28.0,<0.29.0)
Requires-Dist: platon-daytona-api-client (==0.1.5)
Requires-Dist: platon-daytona-api-client-async (==0.1.5)
Requires-Dist: pydantic (>=2.4.2,<3.0.0)
Requires-Dist: toml (>=0.10.0,<0.11.0)
Project-URL: Bug Tracker, https://github.com/galaxyeye/daytona/issues
Project-URL: Changelog, https://github.com/galaxyeye/daytona/blob/main/CHANGELOG.md
Project-URL: Documentation, https://galaxyeye.github.io/daytona
Project-URL: Homepage, https://github.com/galaxyeye/daytona
Project-URL: Repository, https://github.com/galaxyeye/daytona
Project-URL: Source Code, https://github.com/galaxyeye/daytona
